[
  {
    "featureType": "all",
    "elementType": "geometry",
    "stylers": [
      {
        "color": "#dde2e3"
      }
    ]
  },
  {
    "featureType": "all",
    "elementType": "labels.text",
    "stylers": [
      {
        "visibility": "simplified"
      },
      {
        "color": "#76a1b3"
      }
    ]
  },
  {
    "featureType": "all",
    "elementType": "labels.text.fill",
    "stylers": [
      {
        "gamma": 0.01
      },
      {
        "lightness": 20
      },
      {
        "color": "#3f86a4"
      }
    ]
  },
  {
    "featureType": "all",
    "elementType": "labels.text.stroke",
    "stylers": [
      {
        "saturation": -31
      },
      {
        "lightness": -33
      },
      {
        "weight": 2
      },
      {
        "gamma": 0.8
      },
      {
        "visibility": "on"
      },
      {
        "color": "#6090a4"
      }
    ]
  },
  {
    "featureType": "all",
    "elementType": "labels.icon",
    "stylers": [
      {
        "visibility": "off"
      }
    ]
  },
  {
    "featureType": "landscape",
    "elementType": "geometry",
    "stylers": [
      {
        "lightness": 30
      },
      {
        "saturation": 30
      }
    ]
  },
  {
    "featureType": "poi",
    "elementType": "geometry",
    "stylers": [
      {
        "saturation": 20
      }
    ]
  },
  {
    "featureType": "poi.attraction",
    "elementType": "all",
    "stylers": [
      {
        "visibility": "on"
      },
      {
        "hue": "#ff0000"
      }
    ]
  },
  {
    "featureType": "poi.attraction",
    "elementType": "geometry",
    "stylers": [
      {
        "visibility": "simplified"
      }
    ]
  },
  {
    "featureType": "poi.attraction",
    "elementType": "geometry.fill",
    "stylers": [
      {
        "color": "#ff0000"
      }
    ]
  },
  {
    "featureType": "poi.attraction",
    "elementType": "geometry.stroke",
    "stylers": [
      {
        "visibility": "simplified"
      }
    ]
  },
  {
    "featureType": "poi.attraction",
    "elementType": "labels",
    "stylers": [
      {
        "visibility": "off"
      }
    ]
  },
  {
    "featureType": "poi.attraction",
    "elementType": "labels.text",
    "stylers": [
      {
        "visibility": "simplified"
      },
      {
        "color": "#a13333"
      }
    ]
  },
  {
    "featureType": "poi.business",
    "elementType": "geometry",
    "stylers": [
      {
        "visibility": "off"
      },
      {
        "hue": "#ff0000"
      },
      {
        "saturation": "10"
      }
    ]
  },
  {
    "featureType": "poi.business",
    "elementType": "labels",
    "stylers": [
      {
        "visibility": "simplified"
      },
      {
        "hue": "#ff0000"
      },
      {
        "lightness": "8"
      },
      {
        "saturation": "-100"
      }
    ]
  },
  {
    "featureType": "poi.park",
    "elementType": "geometry",
    "stylers": [
      {
        "lightness": 20
      },
      {
        "saturation": -20
      },
      {
        "color": "#a5dd8e"
      }
    ]
  },
  {
    "featureType": "road",
    "elementType": "geometry",
    "stylers": [
      {
        "lightness": 10
      },
      {
        "saturation": -30
      },
      {
        "color": "#ffffff"
      }
    ]
  },
  {
    "featureType": "road",
    "elementType": "geometry.stroke",
    "stylers": [
      {
        "saturation": 25
      },
      {
        "lightness": 25
      },
      {
        "visibility": "simplified"
      },
      {
        "color": "#ffffff"
      }
    ]
  },
  {
    "featureType": "road.highway",
    "elementType": "all",
    "stylers": [
      {
        "color": "#bfd0d4"
      }
    ]
  },
  {
    "featureType": "water",
    "elementType": "all",
    "stylers": [
      {
        "lightness": -20
      },
      {
        "color": "#accee1"
      }
    ]
  }
]
